spatial_transformation/__about__.py
spatial_transformation/__init__.py
spatial_transformation/definitions.py
spatial_transformation/position_2d.py
spatial_transformation/position_3d.py
spatial_transformation/rotation_2d.py
spatial_transformation/rotation_3d.py
spatial_transformation/transform_2d.py
spatial_transformation/transform_3d.py
spatial_transformation/transform_manager.py
spatial_transformation/transform_utils.py
spatial_transformation/utils.py
spatial_transformation-1.1.0.dist-info/METADATA
spatial_transformation-1.1.0.dist-info/WHEEL
spatial_transformation-1.1.0.dist-info/licenses/LICENSE
spatial_transformation-1.1.0.dist-info/RECORD
