Metadata-Version: 2.1
Name: spatial-transformation
Version: 1.1.0
Summary: Helper library for operations of spatial transformation
Project-URL: Homepage, https://deveritec.com
Project-URL: Bug Tracker, https://deveritec.com
Author-email: Alexander Mutz <alexander.mutz@deveritec.com>, Anne Bienert <anne.bienert@tu-dresden.de>, Christoph Schwalbe <christoph.schwalbe@deveritec.com>, Jonas Kreissl <jonas.kreissl@deveritec.com>, Martin Eckardt <martin.eckardt@deveritec.com>, Mirko Riedel <mirko.riedel@deveritec.com>
Maintainer-email: Jonas Kreissl <jonas.kreissl@deveritec.com>, Martin Eckardt <martin.eckardt@deveritec.com>, Mirko Riedel <mirko.riedel@deveritec.com>
License-Expression: MIT
License-File: LICENSE
Classifier: License :: OSI Approved :: MIT License
Classifier: Operating System :: OS Independent
Classifier: Programming Language :: Python :: 3
Requires-Python: >=3.10
Requires-Dist: numpy
Requires-Dist: scipy
